djt_mcp_server/__init__.py
djt_mcp_server-0.1.1.dist-info/METADATA
djt_mcp_server-0.1.1.dist-info/WHEEL
djt_mcp_server-0.1.1.dist-info/entry_points.txt
djt_mcp_server-0.1.1.dist-info/RECORD
